cqi/__init__.py
cqi/client.py
cqi/errors.py
cqi/status.py
cqi/version.py
cqi/api/__init__.py
cqi/api/client.py
cqi/api/specification.py
cqi/models/__init__.py
cqi/models/attributes.py
cqi/models/corpora.py
cqi/models/resource.py
cqi/models/subcorpora.py
cqi-0.1.7.dist-info/LICENSE
cqi-0.1.7.dist-info/METADATA
cqi-0.1.7.dist-info/WHEEL
cqi-0.1.7.dist-info/top_level.txt
cqi-0.1.7.dist-info/RECORD
