Metadata-Version: 2.1
Name: cqi
Version: 0.1.7
Summary: A Python library for the IMS Open Corpus Workbench (CWB) corpus query interface (CQi) API.
Home-page: https://github.com/Pevtrick/cqi-py
Author: Patrick Jentsch
Author-email: patrickjentsch@gmx.net
Classifier: Programming Language :: Python :: 3
Classifier: License :: OSI Approved :: MIT License
Classifier: Operating System :: OS Independent
Requires-Python: >=3.5
License-File: LICENSE
